[
  {
    "RequestID": "30506950-cb7a-4aff-95f2-a4034cc7df90",
    "Title": "Faulty Street Light - Outside School",
    "ServiceType": "Electricity \u0026 Street Lighting",
    "Description": "The street light directly outside the entrance of Glenwood High School (address 100 Main Road) is not working. It\u0027s been out for several nights, making the area dark and unsafe for students leaving evening activities.",
    "StreetNumber": "100",
    "StreetAddressLine2": "Main Road",
    "Suburb": "Glenwood",
    "City": "Durban",
    "PostalCode": "4001",
    "Latitude": null,
    "Longitude": null,
    "DateRequested": "2025-11-12T19:25:44.1814208+02:00",
    "Status": "Assigned",
    "PriorityLevel": 1,
    "AssignedDepartment": "Staff-Assigned",
    "CompletedDate": null,
    "Attachments": [],
    "CitizenName": "Thandi",
    "CitizenSurname": "Mkhize",
    "CitizenEmail": "thandi.m@example.com",
    "CitizenCellNumber": "0612345678",
    "TrackingUsername": "ishkar"
  },
  {
    "RequestID": "35897504-e2ce-4f8c-862f-451eebb8d86a",
    "Title": "Burst Water Pipe - Residential Area",
    "ServiceType": "Water \u0026 Sanitation",
    "Description": "There is a burst water pipe on the pavement in front of 25 River Lane. Water has been gushing out for the past few hours, creating a large puddle and wasting water.",
    "StreetNumber": "25",
    "StreetAddressLine2": "River Lane",
    "Suburb": "Umhlanga",
    "City": "Durban",
    "PostalCode": "4319",
    "Latitude": null,
    "Longitude": null,
    "DateRequested": "2025-11-12T19:26:53.3287857+02:00",
    "Status": "Assigned",
    "PriorityLevel": 1,
    "AssignedDepartment": "Staff-Assigned",
    "CompletedDate": null,
    "Attachments": [],
    "CitizenName": "Pieter",
    "CitizenSurname": "Van Wyk",
    "CitizenEmail": "pieter.vw@example.com",
    "CitizenCellNumber": "0834567890",
    "TrackingUsername": "ishkar"
  },
  {
    "RequestID": "4686d1f4-ff55-457f-97d5-2c6eb4499cf4",
    "Title": "Large Pothole - Corner of Oak and Elm",
    "ServiceType": "Roads \u0026 Transport",
    "Description": "There\u0027s a significant pothole at the intersection of Oak Avenue and Elm Street. It\u0027s deep and wide, causing damage to vehicles and posing a hazard to cyclists. It has been there for over a week and is getting worse.",
    "StreetNumber": "N/A",
    "StreetAddressLine2": "Oak Avenue / Elm Street",
    "Suburb": "Morningside",
    "City": "Durban",
    "PostalCode": "4001",
    "Latitude": null,
    "Longitude": null,
    "DateRequested": "2025-11-12T19:23:35.8541927+02:00",
    "Status": "Assigned",
    "PriorityLevel": 1,
    "AssignedDepartment": "Staff-Assigned",
    "CompletedDate": null,
    "Attachments": [
      "/uploads/servicerequest/ce700dba-e226-4536-9b4a-8d34456000e6.jpg"
    ],
    "CitizenName": "Prema",
    "CitizenSurname": "Naidoo",
    "CitizenEmail": "prema.n@example.com",
    "CitizenCellNumber": "0739876543",
    "TrackingUsername": "ishkar"
  },
  {
    "RequestID": "5f6b9ee1-f6bb-426e-9762-81408cf3c129",
    "Title": " Overgrown Public Park - Children\u0027s Playground",
    "ServiceType": "Parks \u0026 Recreation",
    "Description": "The grass and bushes in the children\u0027s playground area of Mitchell Park are severely overgrown. This makes it difficult for children to play safely and potentially hides litter or hazards.",
    "StreetNumber": "N/A",
    "StreetAddressLine2": "Innes Road",
    "Suburb": "Berea",
    "City": "Durban",
    "PostalCode": "4001",
    "Latitude": null,
    "Longitude": null,
    "DateRequested": "2025-11-12T19:27:48.7613407+02:00",
    "Status": "Assigned",
    "PriorityLevel": 1,
    "AssignedDepartment": "Staff-Assigned",
    "CompletedDate": null,
    "Attachments": [],
    "CitizenName": "Aisha",
    "CitizenSurname": "Khan",
    "CitizenEmail": "aisha.k@example.com",
    "CitizenCellNumber": "0745678901",
    "TrackingUsername": "ishkar"
  },
  {
    "RequestID": "8f103806-1bf7-4b9a-b47f-62f671d3b809",
    "Title": "Overflowing Public Bin - Main Street",
    "ServiceType": "Waste Management",
    "Description": "The public waste bin located outside the post office on Main Street has been overflowing for the past two days. Rubbish is spilling onto the pavement, attracting pests.",
    "StreetNumber": "123",
    "StreetAddressLine2": "Main Street",
    "Suburb": "Central Business District",
    "City": "Durban",
    "PostalCode": "4001",
    "Latitude": null,
    "Longitude": null,
    "DateRequested": "2025-11-12T19:11:45.4260749+02:00",
    "Status": "Assigned",
    "PriorityLevel": 1,
    "AssignedDepartment": "Staff-Assigned",
    "CompletedDate": null,
    "Attachments": [
      "/uploads/servicerequest/996f60ba-0635-478d-8874-a79eb691df67.jpg"
    ],
    "CitizenName": "Sipho",
    "CitizenSurname": "Dlamini",
    "CitizenEmail": "sipho.d@example.com",
    "CitizenCellNumber": "0821234567",
    "TrackingUsername": "ishkar"
  },
  {
    "RequestID": "f7a3b62c-b742-4273-acc3-c1cba0423408",
    "Title": "Illegal Dumping and Building Rubble",
    "ServiceType": "Environmental Services",
    "Description": "A significant amount of builder\u0027s rubble, old tires, and household waste has been illegally dumped on the vacant lot next to 50 Kingfisher Road. This is attracting rodents and is a health hazard for the nearby residents.\r\n",
    "StreetNumber": "N/A",
    "StreetAddressLine2": "Kingfisher Road",
    "Suburb": "Phoenix",
    "City": "Durban",
    "PostalCode": "4068",
    "Latitude": null,
    "Longitude": null,
    "DateRequested": "2025-11-12T21:34:20.9136183+02:00",
    "Status": "Assigned",
    "PriorityLevel": 1,
    "AssignedDepartment": "Staff-Assigned",
    "CompletedDate": null,
    "Attachments": [],
    "CitizenName": "Zanele",
    "CitizenSurname": "Govender",
    "CitizenEmail": "zanele.g@example.com",
    "CitizenCellNumber": "0687654321",
    "TrackingUsername": "ishkar"
  }
]